PyrunC3/__init__.py
PyrunC3/mainfuncs.py
PyrunC3/test.py
PyrunC3-0.0.1.dist-info/METADATA
PyrunC3-0.0.1.dist-info/WHEEL
PyrunC3-0.0.1.dist-info/top_level.txt
PyrunC3-0.0.1.dist-info/RECORD
