Metadata-Version: 2.1
Name: PyrunC3
Version: 0.0.1
Summary: Ability to easily run C# from python
Keywords: Python,C#,python,c#,beginner friendly
